rekall_agent/__init__.py
rekall_agent/action.py
rekall_agent/agent.py
rekall_agent/cache.py
rekall_agent/common.py
rekall_agent/config_updater.py
rekall_agent/controller.py
rekall_agent/crypto.py
rekall_agent/crypto_test.py
rekall_agent/flow.py
rekall_agent/hooks.py
rekall_agent/hunts.py
rekall_agent/location.py
rekall_agent/output_plugin.py
rekall_agent/result_collections.py
rekall_agent/result_collections_test.py
rekall_agent/serializer.py
rekall_agent/serializer_test.py
rekall_agent/testlib.py
rekall_agent/client_actions/__init__.py
rekall_agent/client_actions/collect.py
rekall_agent/client_actions/collect_test.py
rekall_agent/client_actions/darwin.py
rekall_agent/client_actions/download.py
rekall_agent/client_actions/files.py
rekall_agent/client_actions/interrogate.py
rekall_agent/client_actions/osquery.py
rekall_agent/client_actions/osquery_test.py
rekall_agent/client_actions/tsk.py
rekall_agent/client_actions/tsk_test.py
rekall_agent/config/__init__.py
rekall_agent/config/agent.py
rekall_agent/flows/__init__.py
rekall_agent/flows/artifact_flow.py
rekall_agent/flows/collect.py
rekall_agent/flows/find.py
rekall_agent/flows/yara.py
rekall_agent/locations/__init__.py
rekall_agent/locations/cloud.py
rekall_agent/locations/cloud_test.py
rekall_agent/locations/files.py
rekall_agent/locations/files_test.py
rekall_agent/locations/http.py
rekall_agent/locations/http_test.py
rekall_agent/messages/__init__.py
rekall_agent/messages/agent.py
rekall_agent/messages/batch.py
rekall_agent/messages/rekall_messages.py
rekall_agent/messages/resources.py
rekall_agent/policies/__init__.py
rekall_agent/policies/encrypted_gcs.py
rekall_agent/policies/files.py
rekall_agent/policies/gcs.py
rekall_agent/servers/__init__.py
rekall_agent/servers/http.py
rekall_agent/ui/__init__.py
rekall_agent/ui/clients.py
rekall_agent/ui/downloads.py
rekall_agent/ui/flows.py
rekall_agent/ui/interactive.py
rekall_agent/ui/ipython.py
rekall_agent-1.6.0.dist-info/DESCRIPTION.rst
rekall_agent-1.6.0.dist-info/METADATA
rekall_agent-1.6.0.dist-info/RECORD
rekall_agent-1.6.0.dist-info/WHEEL
rekall_agent-1.6.0.dist-info/entry_points.txt
rekall_agent-1.6.0.dist-info/metadata.json
rekall_agent-1.6.0.dist-info/top_level.txt
