Metadata-Version: 2.0
Name: rekall-agent
Version: 1.6.0
Summary: Rekall Incident Response Agent
Home-page: https://www.rekall-forensic.com/
Author: The Rekall team
Author-email: rekall-discuss@googlegroups.com
License: GPL
Platform: UNKNOWN
Classifier: Development Status :: 4 - Beta
Classifier: Environment :: Console
Classifier: Operating System :: OS Independent
Classifier: Programming Language :: Python
Requires-Dist: cryptography (==1.4)
Requires-Dist: filelock (==2.0.6)
Requires-Dist: httplib2 (==0.9.2)
Requires-Dist: oauth2client (==3.0.0)
Requires-Dist: pathlib (==1.0.1)
Requires-Dist: portpicker (==1.1.1)
Requires-Dist: rekall-core (>=1.6.0rc1,<1.7)
Requires-Dist: requests (==2.11.1)
